[
    {
        "Id": 3,
        "CountryId": 2,
        "Name": "USMC",
        "UIName": "ui_spec_usmc_name",
        "UIDescription": "ui_spec_usmc_description",
        "Icon": "SPEC_US_Marines",
        "Illustration": "US_SPEC_USMC",
        "ShowInHangar": true,
        "ReconSlots": 3,
        "InfantrySlots": 5,
        "CombatSlots": 4,
        "SupportSlots": 7,
        "LogisticsSlots": 0,
        "HelicoptersSlots": 6,
        "AirSlots": 7,
        "MaxSlots": 32,
        "ReconPoints": 500,
        "InfantryPoints": 1000,
        "CombatPoints": 1000,
        "SupportPoints": 750,
        "LogisticsPoints": 0,
        "HelicoptersPoints": 750,
        "AirPoints": 1000
    },
    {
        "Id": 4,
        "CountryId": 2,
        "Name": "Armored Brigade",
        "UIName": "ui_spec_armored_name",
        "UIDescription": "ui_spec_armored_description",
        "Icon": "SPEC_US_Armored",
        "Illustration": "US_SPEC_ARMORED",
        "ShowInHangar": true,
        "ReconSlots": 4,
        "InfantrySlots": 4,
        "CombatSlots": 6,
        "SupportSlots": 7,
        "LogisticsSlots": 0,
        "HelicoptersSlots": 0,
        "AirSlots": 0,
        "MaxSlots": 21,
        "ReconPoints": 1000,
        "InfantryPoints": 1000,
        "CombatPoints": 1750,
        "SupportPoints": 1250,
        "LogisticsPoints": 0,
        "HelicoptersPoints": 0,
        "AirPoints": 0
    },
    {
        "Id": 5,
        "CountryId": 2,
        "Name": "Airborne infantry",
        "UIName": "ui_spec_airborne_name",
        "UIDescription": "ui_spec_airborne_description",
        "Icon": "SPEC_US_Airmobile",
        "Illustration": "US_SPEC_AIRBORNE",
        "ShowInHangar": true,
        "ReconSlots": 5,
        "InfantrySlots": 6,
        "CombatSlots": 3,
        "SupportSlots": 6,
        "LogisticsSlots": 0,
        "HelicoptersSlots": 6,
        "AirSlots": 7,
        "MaxSlots": 33,
        "ReconPoints": 500,
        "InfantryPoints": 750,
        "CombatPoints": 500,
        "SupportPoints": 750,
        "LogisticsPoints": 0,
        "HelicoptersPoints": 1000,
        "AirPoints": 1500
    },
    {
        "Id": 6,
        "CountryId": 2,
        "Name": "Stryker Cavalry regiment",
        "UIName": "ui_spec_cavstryker_name",
        "UIDescription": "ui_spec_cavstryker_description",
        "Icon": "SPEC_US_Cavalry",
        "Illustration": "US_SPEC_AIRMOBILE",
        "ShowInHangar": true,
        "ReconSlots": 4,
        "InfantrySlots": 3,
        "CombatSlots": 4,
        "SupportSlots": 7,
        "LogisticsSlots": 0,
        "HelicoptersSlots": 0,
        "AirSlots": 4,
        "MaxSlots": 22,
        "ReconPoints": 750,
        "InfantryPoints": 1250,
        "CombatPoints": 750,
        "SupportPoints": 1250,
        "LogisticsPoints": 0,
        "HelicoptersPoints": 0,
        "AirPoints": 1000
    },
    {
        "Id": 7,
        "CountryId": 1,
        "Name": "VDV Brigade",
        "UIName": "ui_spec_vdv_name",
        "UIDescription": "ui_spec_vdv_description",
        "Icon": "SPEC_RU_VDV",
        "Illustration": "RU_SPEC_VDV",
        "ShowInHangar": true,
        "ReconSlots": 7,
        "InfantrySlots": 6,
        "CombatSlots": 2,
        "SupportSlots": 3,
        "LogisticsSlots": 0,
        "HelicoptersSlots": 7,
        "AirSlots": 7,
        "MaxSlots": 32,
        "ReconPoints": 750,
        "InfantryPoints": 1000,
        "CombatPoints": 500,
        "SupportPoints": 500,
        "LogisticsPoints": 0,
        "HelicoptersPoints": 1000,
        "AirPoints": 1250
    },
    {
        "Id": 8,
        "CountryId": 1,
        "Name": "Guard Tank Brigade",
        "UIName": "ui_spec_guardtank_name",
        "UIDescription": "ui_spec_guardtank_description",
        "Icon": "SPEC_RU_Tank",
        "Illustration": "RU_SPEC_TANK",
        "ShowInHangar": true,
        "ReconSlots": 2,
        "InfantrySlots": 4,
        "CombatSlots": 6,
        "SupportSlots": 7,
        "LogisticsSlots": 0,
        "HelicoptersSlots": 0,
        "AirSlots": 0,
        "MaxSlots": 19,
        "ReconPoints": 750,
        "InfantryPoints": 1250,
        "CombatPoints": 1750,
        "SupportPoints": 1250,
        "LogisticsPoints": 0,
        "HelicoptersPoints": 0,
        "AirPoints": 0
    },
    {
        "Id": 9,
        "CountryId": 1,
        "Name": "Motorized Infantry",
        "UIName": "ui_spec_moto_name",
        "UIDescription": "ui_spec_moto_description",
        "Icon": "SPEC_RU_Motostrelki",
        "Illustration": "RU_SPEC_MOTOSTRELKI",
        "ShowInHangar": true,
        "ReconSlots": 5,
        "InfantrySlots": 6,
        "CombatSlots": 0,
        "SupportSlots": 7,
        "LogisticsSlots": 0,
        "HelicoptersSlots": 5,
        "AirSlots": 4,
        "MaxSlots": 27,
        "ReconPoints": 1000,
        "InfantryPoints": 1250,
        "CombatPoints": 0,
        "SupportPoints": 1250,
        "LogisticsPoints": 0,
        "HelicoptersPoints": 750,
        "AirPoints": 750
    },
    {
        "Id": 10,
        "CountryId": 1,
        "Name": "Coastal Troops",
        "UIName": "ui_spec_coastal_name",
        "UIDescription": "ui_spec_coastal_description",
        "Icon": "SPEC_RU_Morskaya",
        "Illustration": "RU_SPEC_MORSKAYA",
        "ShowInHangar": true,
        "ReconSlots": 5,
        "InfantrySlots": 5,
        "CombatSlots": 4,
        "SupportSlots": 7,
        "LogisticsSlots": 0,
        "HelicoptersSlots": 3,
        "AirSlots": 6,
        "MaxSlots": 30,
        "ReconPoints": 750,
        "InfantryPoints": 1000,
        "CombatPoints": 1000,
        "SupportPoints": 750,
        "LogisticsPoints": 0,
        "HelicoptersPoints": 500,
        "AirPoints": 1000
    },
    {
        "Id": 11,
        "CountryId": 3,
        "Name": "Editor",
        "UIName": "Editor",
        "UIDescription": "Mission editor specialization",
        "Icon": null,
        "Illustration": null,
        "ShowInHangar": false,
        "ReconSlots": 64,
        "InfantrySlots": 64,
        "CombatSlots": 64,
        "SupportSlots": 64,
        "LogisticsSlots": 64,
        "HelicoptersSlots": 64,
        "AirSlots": 64,
        "MaxSlots": 448,
        "ReconPoints": 100000,
        "InfantryPoints": 100000,
        "CombatPoints": 100000,
        "SupportPoints": 100000,
        "LogisticsPoints": 100000,
        "HelicoptersPoints": 100000,
        "AirPoints": 100000
    },
    {
        "Id": 12,
        "CountryId": 1,
        "Name": "Defense Forces",
        "UIName": "Defense Forces",
        "UIDescription": "Strategic assets and irregular units defending the country against long range threats and infiltrated enemies.",
        "Icon": "SPEC_RU_Defense",
        "Illustration": "RU_SPEC_DEFENSE",
        "ShowInHangar": false,
        "ReconSlots": 6,
        "InfantrySlots": 4,
        "CombatSlots": 3,
        "SupportSlots": 7,
        "LogisticsSlots": 0,
        "HelicoptersSlots": 4,
        "AirSlots": 7,
        "MaxSlots": 31,
        "ReconPoints": 750,
        "InfantryPoints": 750,
        "CombatPoints": 750,
        "SupportPoints": 1000,
        "LogisticsPoints": 0,
        "HelicoptersPoints": 750,
        "AirPoints": 1000
    },
    {
        "Id": 13,
        "CountryId": 2,
        "Name": "Special Operations Forces",
        "UIName": "ui_spec_socom_name",
        "UIDescription": "ui_spec_socom_description",
        "Icon": "SPEC_US_SOF",
        "Illustration": "US_SPEC_SOF",
        "ShowInHangar": true,
        "ReconSlots": 7,
        "InfantrySlots": 5,
        "CombatSlots": 0,
        "SupportSlots": 0,
        "LogisticsSlots": 0,
        "HelicoptersSlots": 6,
        "AirSlots": 6,
        "MaxSlots": 24,
        "ReconPoints": 1250,
        "InfantryPoints": 1250,
        "CombatPoints": 0,
        "SupportPoints": 0,
        "LogisticsPoints": 0,
        "HelicoptersPoints": 1250,
        "AirPoints": 1250
    },
    {
        "Id": 14,
        "CountryId": 2,
        "Name": "US Navy",
        "UIName": "US Navy",
        "UIDescription": "US navy aviation and ships provide support for the Marine Littoral Regiment.",
        "Icon": "SPEC_US_Navy",
        "Illustration": "US_SPEC_NAVY",
        "ShowInHangar": false,
        "ReconSlots": 7,
        "InfantrySlots": 5,
        "CombatSlots": 2,
        "SupportSlots": 5,
        "LogisticsSlots": 0,
        "HelicoptersSlots": 5,
        "AirSlots": 7,
        "MaxSlots": 31,
        "ReconPoints": 750,
        "InfantryPoints": 750,
        "CombatPoints": 500,
        "SupportPoints": 750,
        "LogisticsPoints": 0,
        "HelicoptersPoints": 750,
        "AirPoints": 1500
    },
    {
        "Id": 15,
        "CountryId": 1,
        "Name": "Mechanized Infantry",
        "UIName": "ui_spec_mech_name",
        "UIDescription": "ui_spec_mech_description",
        "Icon": "SPEC_RU_Mechanized",
        "Illustration": "RU_SPEC_MECHANIZED",
        "ShowInHangar": true,
        "ReconSlots": 3,
        "InfantrySlots": 7,
        "CombatSlots": 4,
        "SupportSlots": 7,
        "LogisticsSlots": 0,
        "HelicoptersSlots": 0,
        "AirSlots": 2,
        "MaxSlots": 23,
        "ReconPoints": 250,
        "InfantryPoints": 1750,
        "CombatPoints": 1250,
        "SupportPoints": 1250,
        "LogisticsPoints": 0,
        "HelicoptersPoints": 0,
        "AirPoints": 500
    }
]